seglearn/__init__.py
seglearn/_version.py
seglearn/base.py
seglearn/datasets.py
seglearn/feature_functions.py
seglearn/pipe.py
seglearn/preprocessing.py
seglearn/split.py
seglearn/transform.py
seglearn/util.py
seglearn/data/watch_dataset.npy
seglearn/tests/__init__.py
seglearn/tests/test_base.py
seglearn/tests/test_feature_functions.py
seglearn/tests/test_pipe.py
seglearn/tests/test_preprocessing.py
seglearn/tests/test_split.py
seglearn/tests/test_transform.py
seglearn/tests/test_util.py
seglearn-1.2.5.dist-info/LICENSE
seglearn-1.2.5.dist-info/METADATA
seglearn-1.2.5.dist-info/WHEEL
seglearn-1.2.5.dist-info/top_level.txt
seglearn-1.2.5.dist-info/RECORD
