Metadata-Version: 2.1
Name: seglearn
Version: 1.2.5
Summary: A template for scikit-learn compatible packages.
Home-page: https://github.com/dmbee/seglearn
Maintainer: David Burns
Maintainer-email: david.mo.burns@gmail.com
License: BSD
Download-URL: https://github.com/dmbee/seglearn
Platform: UNKNOWN
Classifier: Intended Audience :: Science/Research
Classifier: Intended Audience :: Developers
Classifier: License :: OSI Approved :: BSD License
Classifier: Programming Language :: Python
Classifier: Topic :: Software Development
Classifier: Topic :: Scientific/Engineering
Classifier: Operating System :: Microsoft :: Windows
Classifier: Operating System :: POSIX
Classifier: Operating System :: Unix
Classifier: Operating System :: MacOS
Classifier: Programming Language :: Python :: 3.5
Classifier: Programming Language :: Python :: 3.6
Classifier: Programming Language :: Python :: 3.8
Requires-Dist: numpy
Requires-Dist: scipy
Requires-Dist: scikit-learn (>=0.21.3)
Provides-Extra: docs
Requires-Dist: sphinx ; extra == 'docs'
Requires-Dist: sphinx-gallery ; extra == 'docs'
Requires-Dist: sphinx-rtd-theme ; extra == 'docs'
Requires-Dist: numpydoc ; extra == 'docs'
Requires-Dist: matplotlib ; extra == 'docs'
Requires-Dist: keras ; extra == 'docs'
Requires-Dist: pandas ; extra == 'docs'
Requires-Dist: imbalanced-learn (>=0.6.0) ; extra == 'docs'
Provides-Extra: tests
Requires-Dist: pytest ; extra == 'tests'
Requires-Dist: pytest-cov ; extra == 'tests'
